cardano_method/__init__.py
cardano_method/complex.py
cardano_method/cubic.py
cardano_method/test.py
cardano_method-1.2.0.dist-info/METADATA
cardano_method-1.2.0.dist-info/WHEEL
cardano_method-1.2.0.dist-info/top_level.txt
cardano_method-1.2.0.dist-info/RECORD
