Metadata-Version: 2.1
Name: cardano-method
Version: 1.2.0
Summary: A basic cubic equation solver
Home-page: https://github.com/isobarbaric/CardanoMethod
Author: Krish Shah
Author-email: shahkrish2016@gmail.com
Keywords: algebra,cardano,cardano-method,coefficients,complex,complex numbers,cubic,cubic equation,depressed cubic,equation,imaginary,method,polynomial,quadratic equation,real,roots,square root,zeroes
Classifier: Programming Language :: Python :: 3
Classifier: Topic :: Scientific/Engineering :: Mathematics
Classifier: Operating System :: Unix
Classifier: Operating System :: MacOS :: MacOS X
Classifier: Operating System :: Microsoft :: Windows
